README.md
setup.cfg
setup.py
nimiqclient/__init__.py
nimiqclient/nimiq_client.py
nimiqclient.egg-info/PKG-INFO
nimiqclient.egg-info/SOURCES.txt
nimiqclient.egg-info/dependency_links.txt
nimiqclient.egg-info/requires.txt
nimiqclient.egg-info/top_level.txt
nimiqclient.egg-info/zip-safe
nimiqclient/models/__init__.py
nimiqclient/models/account.py
nimiqclient/models/block.py
nimiqclient/models/mempool.py
nimiqclient/models/miner.py
nimiqclient/models/node.py
nimiqclient/models/peer.py
nimiqclient/models/transaction.py
test/__init__.py
test/session_stub.py
test/test_nimiq_client.py
test/fixtures/__init__.py
test/fixtures/account.py
test/fixtures/block.py
test/fixtures/mempool.py
test/fixtures/miner.py
test/fixtures/node.py
test/fixtures/peer.py
test/fixtures/transaction.py