Metadata-Version: 2.1
Name: nimiqclient
Version: 0.1.2
Summary: A python client for the Nimiq JSON-RPC API
Home-page: https://github.com/nimiq-community/python-client
Author: The Nimiq Foundation
Author-email: info@nimiq.com
License: Apache 2.0
Platform: UNKNOWN
Requires-Python: >=2.4
